{
  "db_name": "PostgreSQL",
  "query": "\n                    UPDATE\n                        pipeline_node_execs\n                    SET\n                        status = $1,\n                        result = $2,\n                        finished_at = NOW()\n                    WHERE\n                        id = $3;\n                ",
  "describe": {
    "columns": [],
    "parameters": {
      "Left": [
        {
          "Custom": {
            "name": "exec_status",
            "kind": {
              "Enum": [
                "pending",
                "running",
                "completed",
                "failed"
              ]
            }
          }
        },
        "Json",
        "Uuid"
      ]
    },
    "nullable": []
  },
  "hash": "e4bdfb3029af206be5db2329bc891d14d2360eeb61e53a80db4d39f8368c8884"
}
