{
  "db_name": "PostgreSQL",
  "query": "\n                    SELECT\n                        pipeline_nodes.id,\n                        pipeline_nodes.node_version,\n                        nodes.publisher_name,\n                        nodes.name,\n                        nodes.container_type::TEXT AS container_type,\n                        pipeline_node_connections.from_pipeline_node_output_id AS \"from_pipeline_node_output_id?\"\n                    FROM\n                        pipeline_nodes\n                    LEFT JOIN\n                        nodes ON pipeline_nodes.node_id = nodes.id\n                    LEFT JOIN\n                        pipeline_node_connections\n                        ON pipeline_nodes.id = pipeline_node_connections.to_pipeline_node_input_id\n                        OR pipeline_nodes.id = pipeline_node_connections.from_pipeline_node_output_id\n                    WHERE\n                        pipeline_nodes.pipeline_id = $1;\n                ",
  "describe": {
    "columns": [
      {
        "ordinal": 0,
        "name": "id",
        "type_info": "Uuid"
      },
      {
        "ordinal": 1,
        "name": "node_version",
        "type_info": "Varchar"
      },
      {
        "ordinal": 2,
        "name": "publisher_name",
        "type_info": "Varchar"
      },
      {
        "ordinal": 3,
        "name": "name",
        "type_info": "Varchar"
      },
      {
        "ordinal": 4,
        "name": "container_type",
        "type_info": "Text"
      },
      {
        "ordinal": 5,
        "name": "from_pipeline_node_output_id?",
        "type_info": "Uuid"
      }
    ],
    "parameters": {
      "Left": [
        "Uuid"
      ]
    },
    "nullable": [
      false,
      false,
      false,
      false,
      null,
      false
    ]
  },
  "hash": "4eb23544745468bfbe4c3e0a17410ec0ffb8ecb653d7225ec70ccf3f1f8e92af"
}
